{"paths": {"admin/js/vendor/select2/i18n/af.js": "admin/js/vendor/select2/i18n/af.4f6fcd73488c.js", "admin/js/vendor/select2/i18n/ar.js": "admin/js/vendor/select2/i18n/ar.65aa8e36bf5d.js", "admin/js/vendor/select2/i18n/az.js": "admin/js/vendor/select2/i18n/az.270c257daf81.js", "admin/js/vendor/select2/i18n/bg.js": "admin/js/vendor/select2/i18n/bg.39b8be30d4f0.js", "admin/js/vendor/select2/i18n/bn.js": "admin/js/vendor/select2/i18n/bn.6d42b4dd5665.js", "admin/js/vendor/select2/i18n/bs.js": "admin/js/vendor/select2/i18n/bs.91624382358e.js", "admin/js/vendor/select2/i18n/ca.js": "admin/js/vendor/select2/i18n/ca.a166b745933a.js", "admin/js/vendor/select2/i18n/cs.js": "admin/js/vendor/select2/i18n/cs.4f43e8e7d33a.js", "admin/js/vendor/select2/i18n/da.js": "admin/js/vendor/select2/i18n/da.766346afe4dd.js", "admin/js/vendor/select2/i18n/de.js": "admin/js/vendor/select2/i18n/de.8a1c222b0204.js", "admin/js/vendor/select2/i18n/dsb.js": "admin/js/vendor/select2/i18n/dsb.56372c92d2f1.js", "admin/js/vendor/select2/i18n/el.js": "admin/js/vendor/select2/i18n/el.27097f071856.js", "admin/js/vendor/select2/i18n/en.js": "admin/js/vendor/select2/i18n/en.cf932ba09a98.js", "admin/js/vendor/select2/i18n/es.js": "admin/js/vendor/select2/i18n/es.66dbc2652fb1.js", "admin/js/vendor/select2/i18n/et.js": "admin/js/vendor/select2/i18n/et.2b96fd98289d.js", "admin/js/vendor/select2/i18n/eu.js": "admin/js/vendor/select2/i18n/eu.adfe5c97b72c.js", "admin/js/vendor/select2/i18n/fa.js": "admin/js/vendor/select2/i18n/fa.3b5bd1961cfd.js", "admin/js/vendor/select2/i18n/fi.js": "admin/js/vendor/select2/i18n/fi.614ec42aa9ba.js", "admin/js/vendor/select2/i18n/fr.js": "admin/js/vendor/select2/i18n/fr.05e0542fcfe6.js", "admin/js/vendor/select2/i18n/gl.js": "admin/js/vendor/select2/i18n/gl.d99b1fedaa86.js", "admin/js/vendor/select2/i18n/he.js": "admin/js/vendor/select2/i18n/he.e420ff6cd3ed.js", "admin/js/vendor/select2/i18n/hi.js": "admin/js/vendor/select2/i18n/hi.70640d41628f.js", "admin/js/vendor/select2/i18n/hr.js": "admin/js/vendor/select2/i18n/hr.a2b092cc1147.js", "admin/js/vendor/select2/i18n/hsb.js": "admin/js/vendor/select2/i18n/hsb.fa3b55265efe.js", "admin/js/vendor/select2/i18n/hu.js": "admin/js/vendor/select2/i18n/hu.6ec6039cb8a3.js", "admin/js/vendor/select2/i18n/hy.js": "admin/js/vendor/select2/i18n/hy.c7babaeef5a6.js", "admin/js/vendor/select2/i18n/id.js": "admin/js/vendor/select2/i18n/id.04debded514d.js", "admin/js/vendor/select2/i18n/is.js": "admin/js/vendor/select2/i18n/is.3ddd9a6a97e9.js", "admin/js/vendor/select2/i18n/it.js": "admin/js/vendor/select2/i18n/it.be4fe8d365b5.js", "admin/js/vendor/select2/i18n/ja.js": "admin/js/vendor/select2/i18n/ja.170ae885d74f.js", "admin/js/vendor/select2/i18n/ka.js": "admin/js/vendor/select2/i18n/ka.2083264a54f0.js", "admin/js/vendor/select2/i18n/km.js": "admin/js/vendor/select2/i18n/km.c23089cb06ca.js", "admin/js/vendor/select2/i18n/ko.js": "admin/js/vendor/select2/i18n/ko.e7be6c20e673.js", "admin/js/vendor/select2/i18n/lt.js": "admin/js/vendor/select2/i18n/lt.23c7ce903300.js", "admin/js/vendor/select2/i18n/lv.js": "admin/js/vendor/select2/i18n/lv.08e62128eac1.js", "admin/js/vendor/select2/i18n/mk.js": "admin/js/vendor/select2/i18n/mk.dabbb9087130.js", "admin/js/vendor/select2/i18n/ms.js": "admin/js/vendor/select2/i18n/ms.4ba82c9a51ce.js", "admin/js/vendor/select2/i18n/nb.js": "admin/js/vendor/select2/i18n/nb.da2fce143f27.js", "admin/js/vendor/select2/i18n/ne.js": "admin/js/vendor/select2/i18n/ne.3d79fd3f08db.js", "admin/js/vendor/select2/i18n/nl.js": "admin/js/vendor/select2/i18n/nl.997868a37ed8.js", "admin/js/vendor/select2/i18n/pl.js": "admin/js/vendor/select2/i18n/pl.6031b4f16452.js", "admin/js/vendor/select2/i18n/ps.js": "admin/js/vendor/select2/i18n/ps.38dfa47af9e0.js", "admin/js/vendor/select2/i18n/pt-BR.js": "admin/js/vendor/select2/i18n/pt-BR.e1b294433e7f.js", "admin/js/vendor/select2/i18n/pt.js": "admin/js/vendor/select2/i18n/pt.33b4a3b44d43.js", "admin/js/vendor/select2/i18n/ro.js": "admin/js/vendor/select2/i18n/ro.f75cb460ec3b.js", "admin/js/vendor/select2/i18n/ru.js": "admin/js/vendor/select2/i18n/ru.934aa95f5b5f.js", "admin/js/vendor/select2/i18n/sk.js": "admin/js/vendor/select2/i18n/sk.33d02cef8d11.js", "admin/js/vendor/select2/i18n/sl.js": "admin/js/vendor/select2/i18n/sl.131a78bc0752.js", "admin/js/vendor/select2/i18n/sq.js": "admin/js/vendor/select2/i18n/sq.5636b60d29c9.js", "admin/js/vendor/select2/i18n/sr-Cyrl.js": "admin/js/vendor/select2/i18n/sr-Cyrl.f254bb8c4c7c.js", "admin/js/vendor/select2/i18n/sr.js": "admin/js/vendor/select2/i18n/sr.5ed85a48f483.js", "admin/js/vendor/select2/i18n/sv.js": "admin/js/vendor/select2/i18n/sv.7a9c2f71e777.js", "admin/js/vendor/select2/i18n/th.js": "admin/js/vendor/select2/i18n/th.f38c20b0221b.js", "admin/js/vendor/select2/i18n/tk.js": "admin/js/vendor/select2/i18n/tk.7c572a68c78f.js", "admin/js/vendor/select2/i18n/tr.js": "admin/js/vendor/select2/i18n/tr.b5a0643d1545.js", "admin/js/vendor/select2/i18n/uk.js": "admin/js/vendor/select2/i18n/uk.8cede7f4803c.js", "admin/js/vendor/select2/i18n/vi.js": "admin/js/vendor/select2/i18n/vi.097a5b75b3e1.js", "admin/js/vendor/select2/i18n/zh-CN.js": "admin/js/vendor/select2/i18n/zh-CN.2cff662ec5f9.js", "admin/js/vendor/select2/i18n/zh-TW.js": "admin/js/vendor/select2/i18n/zh-TW.04554a227c2b.js", "admin/css/vendor/select2/LICENSE-SELECT2.md": "admin/css/vendor/select2/LICENSE-SELECT2.f94142512c91.md", "admin/css/vendor/select2/select2.css": "admin/css/vendor/select2/select2.a2194c262648.css", "admin/css/vendor/select2/select2.min.css": "admin/css/vendor/select2/select2.min.9f54e6414f87.css", "admin/js/vendor/jquery/jquery.js": "admin/js/vendor/jquery/jquery.2849239b95f5.js", "admin/js/vendor/jquery/jquery.min.js": "admin/js/vendor/jquery/jquery.min.8fb8fee4fcc3.js", "admin/js/vendor/jquery/LICENSE.txt": "admin/js/vendor/jquery/LICENSE.de877aa6d744.txt", "admin/js/vendor/select2/LICENSE.md": "admin/js/vendor/select2/LICENSE.f94142512c91.md", "admin/js/vendor/select2/select2.full.js": "admin/js/vendor/select2/select2.full.c2afdeda3058.js", "admin/js/vendor/select2/select2.full.min.js": "admin/js/vendor/select2/select2.full.min.fcd7500d8e13.js", "admin/js/vendor/xregexp/LICENSE.txt": "admin/js/vendor/xregexp/LICENSE.bf79e414957a.txt", "admin/js/vendor/xregexp/xregexp.js": "admin/js/vendor/xregexp/xregexp.efda034b9537.js", "admin/js/vendor/xregexp/xregexp.min.js": "admin/js/vendor/xregexp/xregexp.min.b0439563a5d3.js", "admin/img/gis/move_vertex_off.svg": "admin/img/gis/move_vertex_off.7a23bf31ef8a.svg", "admin/img/gis/move_vertex_on.svg": "admin/img/gis/move_vertex_on.0047eba25b67.svg", "admin/js/admin/DateTimeShortcuts.js": "admin/js/admin/DateTimeShortcuts.300591891b2b.js", "admin/js/admin/RelatedObjectLookups.js": "admin/js/admin/RelatedObjectLookups.de5309ac06dd.js", "rest_framework/docs/css/base.css": "rest_framework/docs/css/base.e630f8f4990e.css", "rest_framework/docs/css/highlight.css": "rest_framework/docs/css/highlight.e0e4d973c6d7.css", "rest_framework/docs/css/jquery.json-view.min.css": "rest_framework/docs/css/jquery.json-view.min.a2e6beeb6710.css", "rest_framework/docs/img/favicon.ico": "rest_framework/docs/img/favicon.5195b4d0f3eb.ico", "rest_framework/docs/img/grid.png": "rest_framework/docs/img/grid.a4b938cf382b.png", "rest_framework/docs/js/api.js": "rest_framework/docs/js/api.18a5ba8a1bd8.js", "rest_framework/docs/js/highlight.pack.js": "rest_framework/docs/js/highlight.pack.479b5f21dcba.js", "rest_framework/docs/js/jquery.json-view.min.js": "rest_framework/docs/js/jquery.json-view.min.b7c2d6981377.js", "admin/css/autocomplete.css": "admin/css/autocomplete.4a81fc4242d0.css", "admin/css/base.css": "admin/css/base.01580fff1759.css", "admin/css/changelists.css": "admin/css/changelists.ae46354f4e80.css", "admin/css/dark_mode.css": "admin/css/dark_mode.4e3d1504ca81.css", "admin/css/dashboard.css": "admin/css/dashboard.be83f13e4369.css", "admin/css/fonts.css": "admin/css/fonts.168bab448fee.css", "admin/css/forms.css": "admin/css/forms.c192d1ec6902.css", "admin/css/login.css": "admin/css/login.586129c60a93.css", "admin/css/nav_sidebar.css": "admin/css/nav_sidebar.30423191f399.css", "admin/css/responsive.css": "admin/css/responsive.02281633b5f1.css", "admin/css/responsive_rtl.css": "admin/css/responsive_rtl.e13ae754cceb.css", "admin/css/rtl.css": "admin/css/rtl.8473f45bd49b.css", "admin/css/widgets.css": "admin/css/widgets.00318bc424d3.css", "admin/fonts/LICENSE.txt": "admin/fonts/LICENSE.d273d63619c9.txt", "admin/fonts/README.txt": "admin/fonts/README.ab99e6b541ea.txt", "admin/fonts/Roboto-Bold-webfont.woff": "admin/fonts/Roboto-Bold-webfont.50d75e48e0a3.woff", "admin/fonts/Roboto-Light-webfont.woff": "admin/fonts/Roboto-Light-webfont.c73eb1ceba33.woff", "admin/fonts/Roboto-Regular-webfont.woff": "admin/fonts/Roboto-Regular-webfont.35b07eb2f871.woff", "admin/img/calendar-icons.svg": "admin/img/calendar-icons.39b290681a8b.svg", "admin/img/icon-addlink.svg": "admin/img/icon-addlink.d519b3bab011.svg", "admin/img/icon-alert.svg": "admin/img/icon-alert.034cc7d8a67f.svg", "admin/img/icon-calendar.svg": "admin/img/icon-calendar.ac7aea671bea.svg", "admin/img/icon-changelink.svg": "admin/img/icon-changelink.18d2fd706348.svg", "admin/img/icon-clock.svg": "admin/img/icon-clock.e1d4dfac3f2b.svg", "admin/img/icon-deletelink.svg": "admin/img/icon-deletelink.564ef9dc3854.svg", "admin/img/icon-no.svg": "admin/img/icon-no.439e821418cd.svg", "admin/img/icon-unknown-alt.svg": "admin/img/icon-unknown-alt.81536e128bb6.svg", "admin/img/icon-unknown.svg": "admin/img/icon-unknown.a18cb4398978.svg", "admin/img/icon-viewlink.svg": "admin/img/icon-viewlink.41eb31f7826e.svg", "admin/img/icon-yes.svg": "admin/img/icon-yes.d2f9f035226a.svg", "admin/img/inline-delete.svg": "admin/img/inline-delete.fec1b761f254.svg", "admin/img/LICENSE": "admin/img/LICENSE.2c54f4e1ca1c", "admin/img/README.txt": "admin/img/README.a70711a38d87.txt", "admin/img/search.svg": "admin/img/search.7cf54ff789c6.svg", "admin/img/selector-icons.svg": "admin/img/selector-icons.b4555096cea2.svg", "admin/img/sorting-icons.svg": "admin/img/sorting-icons.3a097b59f104.svg", "admin/img/tooltag-add.svg": "admin/img/tooltag-add.e59d620a9742.svg", "admin/img/tooltag-arrowright.svg": "admin/img/tooltag-arrowright.bbfb788a849e.svg", "admin/js/actions.js": "admin/js/actions.eac7e3441574.js", "admin/js/autocomplete.js": "admin/js/autocomplete.01591ab27be7.js", "admin/js/calendar.js": "admin/js/calendar.f8a5d055eb33.js", "admin/js/cancel.js": "admin/js/cancel.ecc4c5ca7b32.js", "admin/js/change_form.js": "admin/js/change_form.9d8ca4f96b75.js", "admin/js/collapse.js": "admin/js/collapse.f84e7410290f.js", "admin/js/core.js": "admin/js/core.5d6b384a08b5.js", "admin/js/filters.js": "admin/js/filters.295a9d3d8b6a.js", "admin/js/inlines.js": "admin/js/inlines.22d4d93c00b4.js", "admin/js/jquery.init.js": "admin/js/jquery.init.b7781a0897fc.js", "admin/js/nav_sidebar.js": "admin/js/nav_sidebar.36a64ecb39ed.js", "admin/js/popup_response.js": "admin/js/popup_response.c6cc78ea5551.js", "admin/js/prepopulate.js": "admin/js/prepopulate.bd2361dfd64d.js", "admin/js/prepopulate_init.js": "admin/js/prepopulate_init.6cac7f3105b8.js", "admin/js/SelectBox.js": "admin/js/SelectBox.8161741c7647.js", "admin/js/SelectFilter2.js": "admin/js/SelectFilter2.3f53e33c88d6.js", "admin/js/urlify.js": "admin/js/urlify.25cc3eac8123.js", "img/svg/arrow-right.svg": "img/svg/arrow-right.2e433ce8995a.svg", "img/svg/bx-time-five.svg": "img/svg/bx-time-five.da2d73936b64.svg", "img/svg/chat.svg": "img/svg/chat.87e10e01c68f.svg", "img/svg/circle.svg": "img/svg/circle.07838f7749d2.svg", "img/svg/setting.svg": "img/svg/setting.75b6f6294b43.svg", "img/svg/skill-level.svg": "img/svg/skill-level.aff6c502c1b4.svg", "img/svg/step-one-fill.svg": "img/svg/step-one-fill.ab4f46ff3ed1.svg", "img/svg/step-one-outline.svg": "img/svg/step-one-outline.80d121ffbf8d.svg", "img/svg/step-three-fill.svg": "img/svg/step-three-fill.d0b3e51841a7.svg", "img/svg/step-three-outline.svg": "img/svg/step-three-outline.653bc533733a.svg", "img/svg/step-two-fill.svg": "img/svg/step-two-fill.49a155438211.svg", "img/svg/step-two-outline.svg": "img/svg/step-two-outline.42b1a305b838.svg", "img/svg/task.svg": "img/svg/task.0649fff87dbb.svg", "img/svg/trophy-fill.svg": "img/svg/trophy-fill.b72655875f80.svg", "img/svg/users-solid.svg": "img/svg/users-solid.54475bbd4f43.svg", "rest_framework/css/bootstrap-theme.min.css": "rest_framework/css/bootstrap-theme.min.1d4b05b397c3.css", "rest_framework/css/bootstrap-theme.min.css.map": "rest_framework/css/bootstrap-theme.min.css.51806092cc05.map", "rest_framework/css/bootstrap-tweaks.css": "rest_framework/css/bootstrap-tweaks.46ed116b0edd.css", "rest_framework/css/bootstrap.min.css": "rest_framework/css/bootstrap.min.f17d4516b026.css", "rest_framework/css/bootstrap.min.css.map": "rest_framework/css/bootstrap.min.css.cafbda9c0e9e.map", "rest_framework/css/default.css": "rest_framework/css/default.789dfb5732d7.css", "rest_framework/css/font-awesome-4.0.3.css": "rest_framework/css/font-awesome-4.0.3.c1e1ea213abf.css", "rest_framework/css/prettify.css": "rest_framework/css/prettify.a987f72342ee.css", "rest_framework/fonts/fontawesome-webfont.eot": "rest_framework/fonts/fontawesome-webfont.8b27bc96115c.eot", "rest_framework/fonts/fontawesome-webfont.svg": "rest_framework/fonts/fontawesome-webfont.83e37a11f9d7.svg", "rest_framework/fonts/fontawesome-webfont.ttf": "rest_framework/fonts/fontawesome-webfont.dcb26c7239d8.ttf", "rest_framework/fonts/fontawesome-webfont.woff": "rest_framework/fonts/fontawesome-webfont.3293616ec0c6.woff", "rest_framework/fonts/glyphicons-halflings-regular.eot": "rest_framework/fonts/glyphicons-halflings-regular.f4769f9bdb74.eot", "rest_framework/fonts/glyphicons-halflings-regular.svg": "rest_framework/fonts/glyphicons-halflings-regular.08eda92397ae.svg", "rest_framework/fonts/glyphicons-halflings-regular.ttf": "rest_framework/fonts/glyphicons-halflings-regular.e18bbf611f2a.ttf", "rest_framework/fonts/glyphicons-halflings-regular.woff": "rest_framework/fonts/glyphicons-halflings-regular.fa2772327f55.woff", "rest_framework/fonts/glyphicons-halflings-regular.woff2": "rest_framework/fonts/glyphicons-halflings-regular.448c34a56d69.woff2", "rest_framework/img/glyphicons-halflings-white.png": "rest_framework/img/glyphicons-halflings-white.9bbc6e960299.png", "rest_framework/img/glyphicons-halflings.png": "rest_framework/img/glyphicons-halflings.90233c9067e9.png", "rest_framework/img/grid.png": "rest_framework/img/grid.a4b938cf382b.png", "rest_framework/js/ajax-form.js": "rest_framework/js/ajax-form.0ea6e6052ab5.js", "rest_framework/js/bootstrap.min.js": "rest_framework/js/bootstrap.min.2f34b630ffe3.js", "rest_framework/js/coreapi-0.1.1.js": "rest_framework/js/coreapi-0.1.1.e580e3854595.js", "rest_framework/js/csrf.js": "rest_framework/js/csrf.969930007329.js", "rest_framework/js/default.js": "rest_framework/js/default.5b08897dbdc3.js", "rest_framework/js/jquery-3.5.1.min.js": "rest_framework/js/jquery-3.5.1.min.dc5e7f18c8d3.js", "rest_framework/js/prettify-min.js": "rest_framework/js/prettify-min.709bfcc456c6.js", "css/bootstrap-grid.css": "css/bootstrap-grid.9b5031ec43fe.css", "css/bootstrap-grid.css.map": "css/bootstrap-grid.css.f147f3e4c030.map", "css/bootstrap-grid.min.css": "css/bootstrap-grid.min.7cfef9e92b2f.css", "css/bootstrap-grid.min.css.map": "css/bootstrap-grid.min.css.dba00b988907.map", "css/bootstrap-grid.rtl.css": "css/bootstrap-grid.rtl.b628891aa4f9.css", "css/bootstrap-grid.rtl.css.map": "css/bootstrap-grid.rtl.css.a4fa9e087b77.map", "css/bootstrap-grid.rtl.min.css": "css/bootstrap-grid.rtl.min.60f251743d11.css", "css/bootstrap-grid.rtl.min.css.map": "css/bootstrap-grid.rtl.min.css.90aa3b96a8bf.map", "css/bootstrap-reboot.css": "css/bootstrap-reboot.4e4fe8ef7b21.css", "css/bootstrap-reboot.css.map": "css/bootstrap-reboot.css.850bee7d9144.map", "css/bootstrap-reboot.min.css": "css/bootstrap-reboot.min.86588ad143dc.css", "css/bootstrap-reboot.min.css.map": "css/bootstrap-reboot.min.css.0ac42ed1ae01.map", "css/bootstrap-reboot.rtl.css": "css/bootstrap-reboot.rtl.49858608bb90.css", "css/bootstrap-reboot.rtl.css.map": "css/bootstrap-reboot.rtl.css.f01c1ea9e9f4.map", "css/bootstrap-reboot.rtl.min.css": "css/bootstrap-reboot.rtl.min.65c386e80fd0.css", "css/bootstrap-reboot.rtl.min.css.map": "css/bootstrap-reboot.rtl.min.css.6ac6c6c3f191.map", "css/bootstrap-utilities.css": "css/bootstrap-utilities.ca6b34492050.css", "css/bootstrap-utilities.css.map": "css/bootstrap-utilities.css.d8232cfd5e6a.map", "css/bootstrap-utilities.min.css": "css/bootstrap-utilities.min.2ea3dc9ce0de.css", "css/bootstrap-utilities.min.css.map": "css/bootstrap-utilities.min.css.029a5751fd19.map", "css/bootstrap-utilities.rtl.css": "css/bootstrap-utilities.rtl.4498c6b278b3.css", "css/bootstrap-utilities.rtl.css.map": "css/bootstrap-utilities.rtl.css.599aa5e9388b.map", "css/bootstrap-utilities.rtl.min.css": "css/bootstrap-utilities.rtl.min.8695770291a7.css", "css/bootstrap-utilities.rtl.min.css.map": "css/bootstrap-utilities.rtl.min.css.7fc61fdde7fb.map", "css/bootstrap.css": "css/bootstrap.877cd935acc1.css", "css/bootstrap.css.map": "css/bootstrap.css.81f7531922ec.map", "css/bootstrap.min.css": "css/bootstrap.min.746b3c9652ed.css", "css/bootstrap.min.css.map": "css/bootstrap.min.css.556a2f303bdd.map", "css/bootstrap.rtl.css": "css/bootstrap.rtl.030f3292e2f3.css", "css/bootstrap.rtl.css.map": "css/bootstrap.rtl.css.dd37bb23471f.map", "css/bootstrap.rtl.min.css": "css/bootstrap.rtl.min.d4f2b8ed2cd2.css", "css/bootstrap.rtl.min.css.map": "css/bootstrap.rtl.min.css.be12d09704b2.map", "css/font-awesome.css": "css/font-awesome.52f5eb11d1b7.css", "css/font-awesome.min.css": "css/font-awesome.min.1a97a04605e9.css", "css/mansory.css": "css/mansory.c662be749a02.css", "css/style.css": "css/style.e789379413a9.css", "fonts/DMSans-Bold.ttf": "fonts/DMSans-Bold.b9cec5212f09.ttf", "fonts/DMSans-BoldItalic.ttf": "fonts/DMSans-BoldItalic.f83322c859de.ttf", "fonts/DMSans-Italic.ttf": "fonts/DMSans-Italic.1ea925903e09.ttf", "fonts/DMSans-Medium.ttf": "fonts/DMSans-Medium.24bfda9719b2.ttf", "fonts/DMSans-MediumItalic.ttf": "fonts/DMSans-MediumItalic.a72ea4b3c890.ttf", "fonts/DMSans-Regular.ttf": "fonts/DMSans-Regular.7c217bc94338.ttf", "fonts/fontawesome-webfont.eot": "fonts/fontawesome-webfont.674f50d287a8.eot", "fonts/fontawesome-webfont.svg": "fonts/fontawesome-webfont.acf3dcb7ff75.svg", "fonts/fontawesome-webfont.ttf": "fonts/fontawesome-webfont.b06871f281fe.ttf", "fonts/fontawesome-webfont.woff": "fonts/fontawesome-webfont.fee66e712a8a.woff", "fonts/fontawesome-webfont.woff2": "fonts/fontawesome-webfont.af7ae505a9ee.woff2", "fonts/FontAwesome.otf": "fonts/FontAwesome.0d2717cd5d85.otf", "fonts/Oswald-Bold.ttf": "fonts/Oswald-Bold.452bfeb5bf78.ttf", "fonts/Oswald-ExtraLight.ttf": "fonts/Oswald-ExtraLight.bae2f0108b0a.ttf", "fonts/Oswald-Light.ttf": "fonts/Oswald-Light.6ee38c23e546.ttf", "fonts/Oswald-Medium.ttf": "fonts/Oswald-Medium.14cf874b374c.ttf", "fonts/Oswald-Regular.ttf": "fonts/Oswald-Regular.a7ccbd3cd9a9.ttf", "fonts/Oswald-SemiBold.ttf": "fonts/Oswald-SemiBold.6a5d13d32695.ttf", "fonts/Oswald-VariableFont_wght.ttf": "fonts/Oswald-VariableFont_wght.ca399fd2286e.ttf", "img/clock.jpg": "img/clock.fa5ad53b73c7.jpg", "img/escape-game.jpg": "img/escape-game.3029bf1cb0c0.jpg", "img/faq.png": "img/faq.4bff69c22047.png", "img/labyrinth.jpg": "img/labyrinth.e4f0f75aa42a.jpg", "img/le-laboratoire-explosif.jpg": "img/le-laboratoire-explosif.0d2752849ef6.jpg", "img/map.jpg": "img/map.f9a4075bc8d5.jpg", "img/pattern.png": "img/pattern.33bfd160b9b7.png", "img/prison_maudite_hollandais_volant.jpg": "img/prison_maudite_hollandais_volant.0f690df7c59f.jpg", "img/puzzle.jpg": "img/puzzle.0e1742a858f2.jpg", "img/room.jpg": "img/room.a8b948ca24c9.jpg", "js/booking.js": "js/booking.0db889423c5a.js", "js/bootstrap.bundle.js": "js/bootstrap.bundle.7e83d70c441e.js", "js/bootstrap.bundle.js.map": "js/bootstrap.bundle.js.b3e5aada63cd.map", "js/bootstrap.bundle.min.js": "js/bootstrap.bundle.min.7afae2f97b31.js", "js/bootstrap.bundle.min.js.map": "js/bootstrap.bundle.min.js.1c5cdadb36e7.map", "js/bootstrap.esm.js": "js/bootstrap.esm.ec75d715e244.js", "js/bootstrap.esm.js.map": "js/bootstrap.esm.js.45581a9d7a3f.map", "js/bootstrap.esm.min.js": "js/bootstrap.esm.min.2a092b5bb155.js", "js/bootstrap.esm.min.js.map": "js/bootstrap.esm.min.js.6a8aaae67052.map", "js/bootstrap.js": "js/bootstrap.377c8bd13eba.js", "js/bootstrap.js.map": "js/bootstrap.js.b6bb6d3fe62c.map", "js/bootstrap.min.js": "js/bootstrap.min.0a40007b6de0.js", "js/bootstrap.min.js.map": "js/bootstrap.min.js.2a242f48a34a.map", "js/date.js": "js/date.72dbaf196e2c.js", "js/main.85741bff.js": "js/main.85741bff.397cad46ceba.js"}, "version": "1.0"}